netmiko_bridge/__init__.py
netmiko_bridge/connect_handler_decorator.py
netmiko_bridge/vendor_getter.py
netmiko_bridge-0.1.1.dist-info/LICENSE
netmiko_bridge-0.1.1.dist-info/METADATA
netmiko_bridge-0.1.1.dist-info/WHEEL
netmiko_bridge-0.1.1.dist-info/top_level.txt
netmiko_bridge-0.1.1.dist-info/RECORD
