Metadata-Version: 2.1
Name: netmiko-bridge
Version: 0.1.1
Summary: A decorator for Netmiko vendor driver extension.
Author-email: "shuai w." <x@ousui.org>
License: MIT License
Project-URL: Homepage, https://github.com/ousui/netmiko_bridge
Project-URL: Bug Tracker, https://github.com/ousui/netmiko_bridge/issues
Keywords: netmiko
Classifier: Programming Language :: Python :: 3
Classifier: License :: OSI Approved :: MIT License
Classifier: Operating System :: OS Independent
Requires-Python: >=3.6
License-File: LICENSE
Requires-Dist: netmiko
